df_diskcache-0.1.0.dist-info/licenses/LICENSE
dfdiskcache/__init__.py
dfdiskcache/__version__.py
dfdiskcache/_core.py
dfdiskcache/logger.py
dfdiskcache/py.typed
df_diskcache-0.1.0.dist-info/METADATA
df_diskcache-0.1.0.dist-info/WHEEL
df_diskcache-0.1.0.dist-info/top_level.txt
df_diskcache-0.1.0.dist-info/RECORD
